RdLib/Kalman.py
RdLib/Rd.py
RdLib/RdDriver.py
RdLib/__init__.py
RdLib/config.py
RdLib-0.9.dist-info/METADATA
RdLib-0.9.dist-info/WHEEL
RdLib-0.9.dist-info/top_level.txt
RdLib-0.9.dist-info/RECORD
