Metadata-Version: 2.1
Name: RdLib
Version: 0.9
Summary: Simple library to communicate with Rd03D and HLK-LD2450 radar via serial on Raspberry Pi
Home-page: https://github.com/G20Michu/RdLib
Author: G20Michu
Author-email: G20Michu@proton.me
Classifier: Programming Language :: Python :: 3
Classifier: License :: Other/Proprietary License
Classifier: Operating System :: OS Independent
Requires-Python: >=3.7
Requires-Dist: matplotlib
Requires-Dist: numpy
